bintangbuddy/__init__.py
bintangbuddy/config.py
bintangbuddy/schedules.py
bintang_buddy-0.1.0.dist-info/LICENSE.txt
bintang_buddy-0.1.0.dist-info/METADATA
bintang_buddy-0.1.0.dist-info/WHEEL
bintang_buddy-0.1.0.dist-info/entry_points.txt
bintang_buddy-0.1.0.dist-info/top_level.txt
bintang_buddy-0.1.0.dist-info/RECORD
