Metadata-Version: 2.1
Name: bintang-buddy
Version: 0.1.0
Summary: Bintang Badminton Court Availability Finder
License: MIT License
Keywords: bintang,badminton
Classifier: Programming Language :: Python :: 3
Requires-Python: >=3.7
License-File: LICENSE.txt
Requires-Dist: click
Requires-Dist: pandas
Requires-Dist: requests
Requires-Dist: tqdm
Requires-Dist: prettytable
Provides-Extra: dev
Requires-Dist: black ; extra == 'dev'
Requires-Dist: isort ; extra == 'dev'
Requires-Dist: flake8 ; extra == 'dev'
